Metadata-Version: 1.0
Name: natdabprob
Version: 0.1
Summary: Binomial and Gaussian distributions
Home-page: UNKNOWN
Author: UNKNOWN
Author-email: UNKNOWN
License: UNKNOWN
Platform: UNKNOWN
